pytest_stub/__init__.py
pytest_stub/stub.py
pytest_stub/toolbox.py
pytest_stub/utils.py
pytest_stub-1.1.0.dist-info/AUTHORS
pytest_stub-1.1.0.dist-info/LICENSE
pytest_stub-1.1.0.dist-info/METADATA
pytest_stub-1.1.0.dist-info/WHEEL
pytest_stub-1.1.0.dist-info/entry_points.txt
pytest_stub-1.1.0.dist-info/top_level.txt
pytest_stub-1.1.0.dist-info/RECORD
